traceai_instructor/__init__.py
traceai_instructor/_wrappers.py
traceai_instructor/version.py
traceai_instructor-0.1.8.dist-info/METADATA
traceai_instructor-0.1.8.dist-info/WHEEL
traceai_instructor-0.1.8.dist-info/RECORD
